LICENSE
kayak/__init__.py
kayak/app.py
kayak/ksql/__init__.py
kayak/ksql/ksql_service.py
kayak/ksql/models.py
kayak/renderables/__init__.py
kayak/renderables/kayak_name.py
kayak/renderables/server_info.py
kayak/styles/__init__.py
kayak/styles/colors.py
kayak/tui.css
kayak/tui.py
kayak-0.2.8.dist-info/LICENSE
kayak-0.2.8.dist-info/METADATA
kayak-0.2.8.dist-info/WHEEL
kayak-0.2.8.dist-info/entry_points.txt
kayak-0.2.8.dist-info/RECORD
