Metadata-Version: 2.1
Name: kayak
Version: 0.2.8
Summary: kayak is a ksqlDB TUI (text user interface)
Home-page: https://github.com/sauljabin/kayak
License: MIT
Keywords: kafka,kayak
Author: Saúl Piña
Author-email: sauljabin@gmail.com
Requires-Python: >=3.10,<4.0
Classifier: Environment :: Console
Classifier: License :: OSI Approved :: MIT License
Classifier: Operating System :: MacOS
Classifier: Operating System :: Unix
Classifier: Programming Language :: Python :: 3
Classifier: Programming Language :: Python :: 3.10
Classifier: Programming Language :: Python :: 3.11
Requires-Dist: click (>=8,<9)
Requires-Dist: httpx[http2] (>=0,<1)
Requires-Dist: pyfiglet
Requires-Dist: rich (>=13,<14)
Requires-Dist: textual
Project-URL: Documentation, https://github.com/sauljabin/kayak
Project-URL: Repository, https://github.com/sauljabin/kayak
